README.md
setup.py
tdone/__init__.py
tdone/pricer.py
tdone.egg-info/PKG-INFO
tdone.egg-info/SOURCES.txt
tdone.egg-info/dependency_links.txt
tdone.egg-info/requires.txt
tdone.egg-info/top_level.txt