Metadata-Version: 2.1
Name: tdone
Version: 0.1.2
Summary: TD ONE: A Python Package for Banking and Pricing
Home-page: https://github.com/tpdrg/tdone
Author: Behrang Dadsetan
Author-email: behrang.dadsetan@tpdrg.com
License: BSD 2-clause
Classifier: Development Status :: 5 - Production/Stable
Classifier: Intended Audience :: Developers
Classifier: License :: OSI Approved :: BSD License
Classifier: Operating System :: POSIX :: Linux
Classifier: Operating System :: Microsoft :: Windows
Classifier: Programming Language :: Python :: 3.7
Classifier: Programming Language :: Python :: 3.8
Classifier: Programming Language :: Python :: 3.9
Classifier: Programming Language :: Python :: 3.10
Classifier: Programming Language :: Python :: 3.11
Requires-Dist: pika>=1.3.2
